{
  "id": "528d4f9b-c77d-4486-a689-24a8824dfa94",
  "prevIds": [
    "c9df2a60-6ebb-4fd4-b9ea-5188abb554b6"
  ],
  "version": "8",
  "dialect": "postgres",
  "ddl": [
    {
      "isRlsEnabled": false,
      "name": "api_keys",
      "schema": "public",
      "entityType": "tables"
    },
    {
      "columns": [
        "id"
      ],
      "nameExplicit": false,
      "name": "api_keys_pkey",
      "schema": "public",
      "table": "api_keys",
      "entityType": "pks"
    },
    {
      "type": "uuid",
      "typeSchema": null,
      "notNull": true,
      "dimensions": 0,
      "default": "gen_random_uuid()",
      "generated": null,
      "identity": null,
      "name": "id",
      "schema": "public",
      "table": "api_keys",
      "entityType": "columns"
    },
    {
      "type": "uuid",
      "typeSchema": null,
      "notNull": true,
      "dimensions": 0,
      "default": null,
      "generated": null,
      "identity": null,
      "name": "user_id",
      "schema": "public",
      "table": "api_keys",
      "entityType": "columns"
    },
    {
      "type": "varchar(500)",
      "typeSchema": null,
      "notNull": true,
      "dimensions": 0,
      "default": null,
      "generated": null,
      "identity": null,
      "name": "encrypted_key",
      "schema": "public",
      "table": "api_keys",
      "entityType": "columns"
    },
    {
      "type": "varchar(255)",
      "typeSchema": null,
      "notNull": true,
      "dimensions": 0,
      "default": null,
      "generated": null,
      "identity": null,
      "name": "provider",
      "schema": "public",
      "table": "api_keys",
      "entityType": "columns"
    },
    {
      "type": "timestamp",
      "typeSchema": null,
      "notNull": false,
      "dimensions": 0,
      "default": "now()",
      "generated": null,
      "identity": null,
      "name": "created_at",
      "schema": "public",
      "table": "api_keys",
      "entityType": "columns"
    },
    {
      "nameExplicit": false,
      "columns": [
        "user_id"
      ],
      "schemaTo": "public",
      "tableTo": "users",
      "columnsTo": [
        "id"
      ],
      "onUpdate": "NO ACTION",
      "onDelete": "NO ACTION",
      "name": "api_keys_user_id_users_id_fk",
      "schema": "public",
      "table": "api_keys",
      "entityType": "fks"
    },
    {
      "isRlsEnabled": false,
      "name": "chats",
      "schema": "public",
      "entityType": "tables"
    },
    {
      "columns": [
        "id"
      ],
      "nameExplicit": false,
      "name": "chats_pkey",
      "schema": "public",
      "table": "chats",
      "entityType": "pks"
    },
    {
      "type": "uuid",
      "typeSchema": null,
      "notNull": true,
      "dimensions": 0,
      "default": null,
      "generated": null,
      "identity": null,
      "name": "id",
      "schema": "public",
      "table": "chats",
      "entityType": "columns"
    },
    {
      "type": "uuid",
      "typeSchema": null,
      "notNull": true,
      "dimensions": 0,
      "default": null,
      "generated": null,
      "identity": null,
      "name": "user_id",
      "schema": "public",
      "table": "chats",
      "entityType": "columns"
    },
    {
      "type": "varchar(100)",
      "typeSchema": null,
      "notNull": true,
      "dimensions": 0,
      "default": null,
      "generated": null,
      "identity": null,
      "name": "title",
      "schema": "public",
      "table": "chats",
      "entityType": "columns"
    },
    {
      "type": "varchar(100)",
      "typeSchema": null,
      "notNull": true,
      "dimensions": 0,
      "default": null,
      "generated": null,
      "identity": null,
      "name": "model",
      "schema": "public",
      "table": "chats",
      "entityType": "columns"
    },
    {
      "type": "timestamp",
      "typeSchema": null,
      "notNull": true,
      "dimensions": 0,
      "default": "now()",
      "generated": null,
      "identity": null,
      "name": "created_at",
      "schema": "public",
      "table": "chats",
      "entityType": "columns"
    },
    {
      "nameExplicit": false,
      "columns": [
        "user_id"
      ],
      "schemaTo": "public",
      "tableTo": "users",
      "columnsTo": [
        "id"
      ],
      "onUpdate": "NO ACTION",
      "onDelete": "CASCADE",
      "name": "chats_user_id_users_id_fk",
      "schema": "public",
      "table": "chats",
      "entityType": "fks"
    },
    {
      "isRlsEnabled": false,
      "name": "messages",
      "schema": "public",
      "entityType": "tables"
    },
    {
      "columns": [
        "id"
      ],
      "nameExplicit": false,
      "name": "messages_pkey",
      "schema": "public",
      "table": "messages",
      "entityType": "pks"
    },
    {
      "type": "uuid",
      "typeSchema": null,
      "notNull": true,
      "dimensions": 0,
      "default": null,
      "generated": null,
      "identity": null,
      "name": "id",
      "schema": "public",
      "table": "messages",
      "entityType": "columns"
    },
    {
      "type": "varchar",
      "typeSchema": null,
      "notNull": true,
      "dimensions": 0,
      "default": null,
      "generated": null,
      "identity": null,
      "name": "role",
      "schema": "public",
      "table": "messages",
      "entityType": "columns"
    },
    {
      "type": "uuid",
      "typeSchema": null,
      "notNull": true,
      "dimensions": 0,
      "default": null,
      "generated": null,
      "identity": null,
      "name": "chat_id",
      "schema": "public",
      "table": "messages",
      "entityType": "columns"
    },
    {
      "type": "uuid",
      "typeSchema": null,
      "notNull": true,
      "dimensions": 0,
      "default": null,
      "generated": null,
      "identity": null,
      "name": "user_id",
      "schema": "public",
      "table": "messages",
      "entityType": "columns"
    },
    {
      "type": "varchar",
      "typeSchema": null,
      "notNull": true,
      "dimensions": 0,
      "default": null,
      "generated": null,
      "identity": null,
      "name": "content",
      "schema": "public",
      "table": "messages",
      "entityType": "columns"
    },
    {
      "type": "timestamp",
      "typeSchema": null,
      "notNull": true,
      "dimensions": 0,
      "default": "now()",
      "generated": null,
      "identity": null,
      "name": "created_at",
      "schema": "public",
      "table": "messages",
      "entityType": "columns"
    },
    {
      "type": "smallint",
      "typeSchema": null,
      "notNull": true,
      "dimensions": 0,
      "default": null,
      "generated": null,
      "identity": null,
      "name": "tokens",
      "schema": "public",
      "table": "messages",
      "entityType": "columns"
    },
    {
      "type": "varchar(100)",
      "typeSchema": null,
      "notNull": true,
      "dimensions": 0,
      "default": null,
      "generated": null,
      "identity": null,
      "name": "provider",
      "schema": "public",
      "table": "messages",
      "entityType": "columns"
    },
    {
      "type": "smallint",
      "typeSchema": null,
      "notNull": true,
      "dimensions": 0,
      "default": null,
      "generated": null,
      "identity": null,
      "name": "message_order",
      "schema": "public",
      "table": "messages",
      "entityType": "columns"
    },
    {
      "nameExplicit": false,
      "columns": [
        "chat_id"
      ],
      "schemaTo": "public",
      "tableTo": "chats",
      "columnsTo": [
        "id"
      ],
      "onUpdate": "NO ACTION",
      "onDelete": "CASCADE",
      "name": "messages_chat_id_chats_id_fk",
      "schema": "public",
      "table": "messages",
      "entityType": "fks"
    },
    {
      "nameExplicit": false,
      "columns": [
        "user_id"
      ],
      "schemaTo": "public",
      "tableTo": "users",
      "columnsTo": [
        "id"
      ],
      "onUpdate": "NO ACTION",
      "onDelete": "CASCADE",
      "name": "messages_user_id_users_id_fk",
      "schema": "public",
      "table": "messages",
      "entityType": "fks"
    },
    {
      "isRlsEnabled": false,
      "name": "refresh_tokens",
      "schema": "public",
      "entityType": "tables"
    },
    {
      "columns": [
        "id"
      ],
      "nameExplicit": false,
      "name": "refresh_tokens_pkey",
      "schema": "public",
      "table": "refresh_tokens",
      "entityType": "pks"
    },
    {
      "type": "varchar(255)",
      "typeSchema": null,
      "notNull": true,
      "dimensions": 0,
      "default": null,
      "generated": null,
      "identity": null,
      "name": "id",
      "schema": "public",
      "table": "refresh_tokens",
      "entityType": "columns"
    },
    {
      "type": "uuid",
      "typeSchema": null,
      "notNull": true,
      "dimensions": 0,
      "default": null,
      "generated": null,
      "identity": null,
      "name": "user_id",
      "schema": "public",
      "table": "refresh_tokens",
      "entityType": "columns"
    },
    {
      "type": "varchar(500)",
      "typeSchema": null,
      "notNull": true,
      "dimensions": 0,
      "default": null,
      "generated": null,
      "identity": null,
      "name": "access_token",
      "schema": "public",
      "table": "refresh_tokens",
      "entityType": "columns"
    },
    {
      "type": "varchar(255)",
      "typeSchema": null,
      "notNull": true,
      "dimensions": 0,
      "default": null,
      "generated": null,
      "identity": null,
      "name": "ip_address",
      "schema": "public",
      "table": "refresh_tokens",
      "entityType": "columns"
    },
    {
      "type": "timestamp",
      "typeSchema": null,
      "notNull": true,
      "dimensions": 0,
      "default": null,
      "generated": null,
      "identity": null,
      "name": "expiry_date",
      "schema": "public",
      "table": "refresh_tokens",
      "entityType": "columns"
    },
    {
      "type": "timestamp",
      "typeSchema": null,
      "notNull": false,
      "dimensions": 0,
      "default": "now()",
      "generated": null,
      "identity": null,
      "name": "created_at",
      "schema": "public",
      "table": "refresh_tokens",
      "entityType": "columns"
    },
    {
      "nameExplicit": false,
      "columns": [
        "user_id"
      ],
      "schemaTo": "public",
      "tableTo": "users",
      "columnsTo": [
        "id"
      ],
      "onUpdate": "NO ACTION",
      "onDelete": "CASCADE",
      "name": "refresh_tokens_user_id_users_id_fk",
      "schema": "public",
      "table": "refresh_tokens",
      "entityType": "fks"
    },
    {
      "isRlsEnabled": false,
      "name": "summaries",
      "schema": "public",
      "entityType": "tables"
    },
    {
      "columns": [
        "id"
      ],
      "nameExplicit": false,
      "name": "summaries_pkey",
      "schema": "public",
      "table": "summaries",
      "entityType": "pks"
    },
    {
      "type": "uuid",
      "typeSchema": null,
      "notNull": true,
      "dimensions": 0,
      "default": "gen_random_uuid()",
      "generated": null,
      "identity": null,
      "name": "id",
      "schema": "public",
      "table": "summaries",
      "entityType": "columns"
    },
    {
      "type": "uuid",
      "typeSchema": null,
      "notNull": true,
      "dimensions": 0,
      "default": null,
      "generated": null,
      "identity": null,
      "name": "chat_id",
      "schema": "public",
      "table": "summaries",
      "entityType": "columns"
    },
    {
      "type": "uuid",
      "typeSchema": null,
      "notNull": true,
      "dimensions": 0,
      "default": null,
      "generated": null,
      "identity": null,
      "name": "user_id",
      "schema": "public",
      "table": "summaries",
      "entityType": "columns"
    },
    {
      "type": "varchar",
      "typeSchema": null,
      "notNull": true,
      "dimensions": 0,
      "default": "'No previous conversation to summarize.'",
      "generated": null,
      "identity": null,
      "name": "summary",
      "schema": "public",
      "table": "summaries",
      "entityType": "columns"
    },
    {
      "type": "smallint",
      "typeSchema": null,
      "notNull": true,
      "dimensions": 0,
      "default": null,
      "generated": null,
      "identity": null,
      "name": "last_index",
      "schema": "public",
      "table": "summaries",
      "entityType": "columns"
    },
    {
      "type": "timestamp",
      "typeSchema": null,
      "notNull": false,
      "dimensions": 0,
      "default": "now()",
      "generated": null,
      "identity": null,
      "name": "created_at",
      "schema": "public",
      "table": "summaries",
      "entityType": "columns"
    },
    {
      "nameExplicit": false,
      "columns": [
        "chat_id"
      ],
      "schemaTo": "public",
      "tableTo": "chats",
      "columnsTo": [
        "id"
      ],
      "onUpdate": "NO ACTION",
      "onDelete": "CASCADE",
      "name": "summaries_chat_id_chats_id_fk",
      "schema": "public",
      "table": "summaries",
      "entityType": "fks"
    },
    {
      "nameExplicit": false,
      "columns": [
        "user_id"
      ],
      "schemaTo": "public",
      "tableTo": "users",
      "columnsTo": [
        "id"
      ],
      "onUpdate": "NO ACTION",
      "onDelete": "CASCADE",
      "name": "summaries_user_id_users_id_fk",
      "schema": "public",
      "table": "summaries",
      "entityType": "fks"
    },
    {
      "isRlsEnabled": false,
      "name": "token_usage",
      "schema": "public",
      "entityType": "tables"
    },
    {
      "columns": [
        "id"
      ],
      "nameExplicit": false,
      "name": "token_usage_pkey",
      "schema": "public",
      "table": "token_usage",
      "entityType": "pks"
    },
    {
      "type": "uuid",
      "typeSchema": null,
      "notNull": true,
      "dimensions": 0,
      "default": "gen_random_uuid()",
      "generated": null,
      "identity": null,
      "name": "id",
      "schema": "public",
      "table": "token_usage",
      "entityType": "columns"
    },
    {
      "type": "uuid",
      "typeSchema": null,
      "notNull": true,
      "dimensions": 0,
      "default": null,
      "generated": null,
      "identity": null,
      "name": "user_id",
      "schema": "public",
      "table": "token_usage",
      "entityType": "columns"
    },
    {
      "type": "uuid",
      "typeSchema": null,
      "notNull": true,
      "dimensions": 0,
      "default": null,
      "generated": null,
      "identity": null,
      "name": "chat_id",
      "schema": "public",
      "table": "token_usage",
      "entityType": "columns"
    },
    {
      "type": "integer",
      "typeSchema": null,
      "notNull": true,
      "dimensions": 0,
      "default": null,
      "generated": null,
      "identity": null,
      "name": "usage",
      "schema": "public",
      "table": "token_usage",
      "entityType": "columns"
    },
    {
      "type": "timestamp",
      "typeSchema": null,
      "notNull": true,
      "dimensions": 0,
      "default": "now()",
      "generated": null,
      "identity": null,
      "name": "created_at",
      "schema": "public",
      "table": "token_usage",
      "entityType": "columns"
    },
    {
      "nameExplicit": false,
      "columns": [
        "user_id"
      ],
      "schemaTo": "public",
      "tableTo": "users",
      "columnsTo": [
        "id"
      ],
      "onUpdate": "NO ACTION",
      "onDelete": "CASCADE",
      "name": "token_usage_user_id_users_id_fk",
      "schema": "public",
      "table": "token_usage",
      "entityType": "fks"
    },
    {
      "nameExplicit": false,
      "columns": [
        "chat_id"
      ],
      "schemaTo": "public",
      "tableTo": "chats",
      "columnsTo": [
        "id"
      ],
      "onUpdate": "NO ACTION",
      "onDelete": "CASCADE",
      "name": "token_usage_chat_id_chats_id_fk",
      "schema": "public",
      "table": "token_usage",
      "entityType": "fks"
    },
    {
      "isRlsEnabled": false,
      "name": "users",
      "schema": "public",
      "entityType": "tables"
    },
    {
      "columns": [
        "id"
      ],
      "nameExplicit": false,
      "name": "users_pkey",
      "schema": "public",
      "table": "users",
      "entityType": "pks"
    },
    {
      "type": "uuid",
      "typeSchema": null,
      "notNull": true,
      "dimensions": 0,
      "default": "gen_random_uuid()",
      "generated": null,
      "identity": null,
      "name": "id",
      "schema": "public",
      "table": "users",
      "entityType": "columns"
    },
    {
      "type": "varchar(255)",
      "typeSchema": null,
      "notNull": true,
      "dimensions": 0,
      "default": null,
      "generated": null,
      "identity": null,
      "name": "name",
      "schema": "public",
      "table": "users",
      "entityType": "columns"
    },
    {
      "type": "varchar(255)",
      "typeSchema": null,
      "notNull": true,
      "dimensions": 0,
      "default": null,
      "generated": null,
      "identity": null,
      "name": "email",
      "schema": "public",
      "table": "users",
      "entityType": "columns"
    },
    {
      "type": "varchar(255)",
      "typeSchema": null,
      "notNull": true,
      "dimensions": 0,
      "default": null,
      "generated": null,
      "identity": null,
      "name": "password",
      "schema": "public",
      "table": "users",
      "entityType": "columns"
    },
    {
      "nameExplicit": false,
      "columns": [
        "email"
      ],
      "nullsNotDistinct": false,
      "name": "users_email_unique",
      "schema": "public",
      "table": "users",
      "entityType": "uniques"
    }
  ],
  "renames": []
}